NGTube/__init__.py
NGTube/core.py
NGTube/utils.py
NGTube/channel/__init__.py
NGTube/channel/channel.py
NGTube/comments/__init__.py
NGTube/comments/comments.py
NGTube/search/__init__.py
NGTube/search/search.py
NGTube/shorts/__init__.py
NGTube/shorts/shorts.py
NGTube/video/__init__.py
NGTube/video/video.py
ngtube-1.0.3.dist-info/METADATA
ngtube-1.0.3.dist-info/WHEEL
ngtube-1.0.3.dist-info/top_level.txt
ngtube-1.0.3.dist-info/RECORD
